setup.py
akr_probability/__init__.py
akr_probability/binomialdistribution.py
akr_probability/gaussiandistribution.py
akr_probability/generaldistribution.py
akr_probability.egg-info/PKG-INFO
akr_probability.egg-info/SOURCES.txt
akr_probability.egg-info/dependency_links.txt
akr_probability.egg-info/not-zip-safe
akr_probability.egg-info/top_level.txt