Metadata-Version: 2.1
Name: akr-probability
Version: 0.1
Summary: Gaussian akr_probability
Home-page: UNKNOWN
Author: Arishwin Kishaan
Author-email: arishwinkishaan3@gmail.com
License: UNKNOWN
Platform: UNKNOWN
